cointer/__init__.py
cointer-0.1.0.dist-info/LICENSE
cointer-0.1.0.dist-info/METADATA
cointer-0.1.0.dist-info/WHEEL
cointer-0.1.0.dist-info/top_level.txt
cointer-0.1.0.dist-info/RECORD
