Metadata-Version: 2.1
Name: cointer
Version: 0.1.0
Summary: Get crypto-currencies prices easily
Home-page: https://github.com/ThomasMargnac/cointer
Author: Thomas Margnac
License: Apache License 2.0
Project-URL: Bug Tracker, https://github.com/ThomasMargnac/cointer/issues
Keywords: crypto-currencies,blockchain
Classifier: License :: OSI Approved :: Apache Software License
License-File: LICENSE
